cipclient.py
python_cipclient-0.0.2.dist-info/LICENSE
python_cipclient-0.0.2.dist-info/METADATA
python_cipclient-0.0.2.dist-info/WHEEL
python_cipclient-0.0.2.dist-info/top_level.txt
python_cipclient-0.0.2.dist-info/RECORD
