Metadata-Version: 2.1
Name: python-cipclient
Version: 0.0.2
Summary: A Python-based socket client for communicating
Home-page: https://github.com/klenae/python-cipclient
Author: Katherine Lenae
Author-email: klenae@gmail.com
License: UNKNOWN
Keywords: development cip home-automation
Platform: UNKNOWN
Classifier: Development Status :: 3 - Alpha
Classifier: Intended Audience :: Developers
Classifier: Topic :: Home Automation
Classifier: License :: OSI Approved :: MIT License
Classifier: Programming Language :: Python :: 3
Classifier: Operating System :: OS Independent
Classifier: Programming Language :: Python :: 3.6
Classifier: Programming Language :: Python :: 3.7
Classifier: Programming Language :: Python :: 3.8
Requires-Python: >=3.6
